README.md
setup.py
yuleak_api/__init__.py
yuleak_api/client.py
yuleak_api/errors.py
yuleak_api/logs.py
yuleak_api.egg-info/PKG-INFO
yuleak_api.egg-info/SOURCES.txt
yuleak_api.egg-info/dependency_links.txt
yuleak_api.egg-info/requires.txt
yuleak_api.egg-info/top_level.txt
yuleak_api/models/__init__.py
yuleak_api/models/dashboard.py
yuleak_api/models/dnsentry.py
yuleak_api/models/event.py
yuleak_api/models/filter.py
yuleak_api/models/marker.py
yuleak_api/models/node.py
yuleak_api/models/resource.py
yuleak_api/models/server.py