Metadata-Version: 2.1
Name: yuleak-api
Version: 1.5.0
Summary: Python Client for Yuleak API.
Home-page: https://github.com/wanbytes/yuleak-api
Author: Wanbytes SAS
License: Apache 2
Keywords: yuleak api python
Platform: UNKNOWN
Classifier: Environment :: Console
Classifier: Development Status :: 5 - Production/Stable
Classifier: Intended Audience :: Developers
Classifier: Intended Audience :: System Administrators
Classifier: Topic :: Software Development
Classifier: License :: OSI Approved :: Apache Software License
Classifier: Programming Language :: Python
Classifier: Programming Language :: Python :: 2.7
Classifier: Programming Language :: Python :: 3.7
